ana_gces/__init__.py
ana_gces-0.1.0.dist-info/WHEEL
ana_gces-0.1.0.dist-info/METADATA
ana_gces-0.1.0.dist-info/RECORD
