Metadata-Version: 2.1
Name: ana-gces
Version: 0.1.0
Summary: Trabalho Final de GCES
Author: anacarolinarodrigues
Author-email: anacarolinarodrigues480@gmail.com
Requires-Python: >=3.10,<4.0
Classifier: Programming Language :: Python :: 3
Classifier: Programming Language :: Python :: 3.10
Classifier: Programming Language :: Python :: 3.11
